trame/__init__.py
trame/modules/__init__.py
trame/modules/vtk3d.py
trame/widgets/__init__.py
trame/widgets/vtk3d.py
trame_vtk3d/__init__.py
trame_vtk3d/module/__init__.py
trame_vtk3d/module/serve/trame_vtk3d.umd.js
trame_vtk3d/module/serve/vtk3d.js
trame_vtk3d/module/serve/vtk3d.wasm
trame_vtk3d/widgets/__init__.py
trame_vtk3d/widgets/vtk3d.py
trame_vtk3d-0.1.0.dist-info/LICENSE
trame_vtk3d-0.1.0.dist-info/METADATA
trame_vtk3d-0.1.0.dist-info/WHEEL
trame_vtk3d-0.1.0.dist-info/top_level.txt
trame_vtk3d-0.1.0.dist-info/RECORD
