Metadata-Version: 2.1
Name: trame-vtk3d
Version: 0.1.0
Summary: Trame wrapper to WASM bundle of VTK from dicehub
Author: Kitware Inc.
License: Apache Software License
Keywords: Python,Interactive,Web,Application,Framework
Classifier: Development Status :: 4 - Beta
Classifier: Environment :: Web Environment
Classifier: License :: OSI Approved :: Apache Software License
Classifier: Natural Language :: English
Classifier: Operating System :: OS Independent
Classifier: Programming Language :: Python :: 3 :: Only
Classifier: Programming Language :: JavaScript
Classifier: Topic :: Software Development :: Libraries :: Application Frameworks
Classifier: Topic :: Software Development :: Libraries :: Python Modules
License-File: LICENSE
Requires-Dist: trame-client
